magic_admin/__init__.py
magic_admin/config.py
magic_admin/error.py
magic_admin/http_client.py
magic_admin/magic.py
magic_admin/response.py
magic_admin/version.py
magic_admin-2.1.2.dist-info/METADATA
magic_admin-2.1.2.dist-info/WHEEL
magic_admin-2.1.2.dist-info/top_level.txt
magic_admin-2.1.2.dist-info/RECORD
