Metadata-Version: 2.4
Name: magic-admin
Version: 2.1.2
Summary: Magic Python Library
Author-email: Magic <support@magic.link>
License: MIT
Project-URL: Website, https://magic.link
Keywords: magic,python,sdk
Classifier: Development Status :: 3 - Alpha
Classifier: Programming Language :: Python
Classifier: Programming Language :: Python :: 3.11
Classifier: Intended Audience :: Developers
Classifier: Operating System :: OS Independent
Requires-Python: >=3.11
Requires-Dist: requests==2.32.5
Requires-Dist: web3==7.13.0
Requires-Dist: websockets==15.0.1
